pytheline/__init__.py
pytheline/pytheline.py
pytheline-0.0.4.dist-info/METADATA
pytheline-0.0.4.dist-info/RECORD
pytheline-0.0.4.dist-info/WHEEL
pytheline-0.0.4.dist-info/top_level.txt
tests/__init__.py
tests/test_delijn.py
