Metadata-Version: 2.1
Name: pytheline
Version: 0.0.4
Summary: A Python wrapper using the undocumented 'De Lijn' API
Home-page: https://gitlab.com/tjorim/pytheline
Author: Jorim Tielemans
Author-email: tielemans.jorim@gmail.com
License: UNKNOWN
Platform: UNKNOWN
Classifier: Programming Language :: Python :: 3
Classifier: License :: OSI Approved :: MIT License
Classifier: Operating System :: OS Independent
Requires-Python: >=3
Requires-Dist: requests (>=2.0)
